lloyd_drift_demo/__init__.py
lloyd_drift_demo/analyze_session.py
lloyd_drift_demo/drift_types.py
lloyd_drift_demo/override_scores.py
lloyd_drift_demo/devtools/__init__.py
lloyd_drift_demo/devtools/run.py
lloyd_drift_demo/devtools/sandbox_demo/__init__.py
lloyd_drift_demo/devtools/sandbox_demo/app/app.py
lloyd_drift_demo/engine/__init__.py
lloyd_drift_demo/engine/drift_engine.py
lloyd_drift_demo/engine/shared_utils.py
lloyd_drift_demo/engine/test_drift_cases.py
lloyd_drift_demo/engine/token_heatmap_sketch.py
lloyd_drift_demo-0.1.3.dist-info/licenses/LICENSE
lloyd_drift_demo-0.1.3.dist-info/METADATA
lloyd_drift_demo-0.1.3.dist-info/WHEEL
lloyd_drift_demo-0.1.3.dist-info/top_level.txt
lloyd_drift_demo-0.1.3.dist-info/RECORD
