Metadata-Version: 2.4
Name: lloyd_drift_demo
Version: 0.1.3
Summary: LLOYD symbolic drift detection engine
Author-email: "Stephen A. Putman" <putmanmodel@pm.me>
License: Creative Commons Attribution-NonCommercial 4.0 International
Requires-Python: >=3.8
License-File: LICENSE
Requires-Dist: emoji
Requires-Dist: numpy
Requires-Dist: requests
Requires-Dist: rich
Requires-Dist: pandas
Requires-Dist: regex
Requires-Dist: jsonschema
Requires-Dist: streamlit
Requires-Dist: altair
Requires-Dist: textblob
Requires-Dist: scikit-learn
Requires-Dist: tenacity
Requires-Dist: watchdog
Requires-Dist: blinker
Requires-Dist: duckdb
Requires-Dist: this
Dynamic: license-file
